Metadata-Version: 2.1
Name: odoo13-addon-account-credit-control
Version: 13.0.2.4.0
Summary: Account Credit Control
Home-page: https://github.com/OCA/credit-control
Author: Camptocamp,Odoo Community Association (OCA),Okia,Access Bookings,Tecnativa,ACSONE SA/NV
Author-email: support@odoo-community.org
License: AGPL-3
Platform: UNKNOWN
Classifier: Programming Language :: Python
Classifier: Framework :: Odoo
Classifier: Framework :: Odoo :: 13.0
Classifier: License :: OSI Approved :: GNU Affero General Public License v3
Requires-Python: >=3.5
Requires-Dist: odoo (<13.1dev,>=13.0a)
